[
  {
    "simplified": "爱",
    "radical": "爫",
    "frequency": 130,
    "pos": [
      "v",
      "vn",
      "b"
    ],
    "forms": [
      {
        "traditional": "愛",
        "transcriptions": {
          "pinyin": "ài",
          "numeric": "ai4",
          "wadegiles": "ai⁴",
          "bopomofo": "ㄞˋ",
          "romatzyh": "ay"
        },
        "meanings": [
          "to love; to be fond of; to like",
          "affection",
          "to be inclined (to do sth); to tend to (happen)"
        ],
        "classifiers": []
      }
    ]
  },
  {
    "simplified": "爱好",
    "radical": "爫",
    "frequency": 4902,
    "pos": [
      "n",
      "v"
    ],
    "forms": [
      {
        "traditional": "愛好",
        "transcriptions": {
          "pinyin": "ài hào",
          "numeric": "ai4 hao4",
          "wadegiles": "ai⁴ hao⁴",
          "bopomofo": "ㄞˋ ㄏㄠˋ",
          "romatzyh": "ay haw"
        },
        "meanings": [
          "to like; to be fond of; to take pleasure in; to be keen on",
          "interest; hobby"
        ],
        "classifiers": [
          "个"
        ]
      }
    ]
  },
  {
    "simplified": "八",
    "radical": "八",
    "frequency": 1362,
    "pos": [
      "m",
      "t"
    ],
    "forms": [
      {
        "traditional": "八",
        "transcriptions": {
          "pinyin": "bā",
          "numeric": "ba1",
          "wadegiles": "pa¹",
          "bopomofo": "ㄅㄚ",
          "romatzyh": "ba"
        },
        "meanings": [
          "eight; 8"
        ],
        "classifiers": []
      }
    ]
  },
  {
    "simplified": "爸",
    "radical": "父",
    "frequency": 1142,
    "pos": [
      "n"
    ],
    "forms": [
      {
        "traditional": "爸",
        "transcriptions": {
          "pinyin": "bà",
          "numeric": "ba4",
          "wadegiles": "pa⁴",
          "bopomofo": "ㄅㄚˋ",
          "romatzyh": "bah"
        },
        "meanings": [
          "father",
          "dad",
          "pa",
          "papa"
        ],
        "classifiers": []
      }
    ]
  },
  {
    "simplified": "爸爸",
    "radical": "父",
    "frequency": 908,
    "pos": [
      "n"
    ],
    "forms": [
      {
        "traditional": "爸爸",
        "transcriptions": {
          "pinyin": "bà ba",
          "numeric": "ba4 ba5",
          "wadegiles": "pa⁴ ba",
          "bopomofo": "ㄅㄚˋ ba",
          "romatzyh": "bah ba"
        },
        "meanings": [
          "(coll.) father; dad"
        ],
        "classifiers": [
          "个",
          "位"
        ]
      }
    ]
  },
  {
    "simplified": "吧",
    "radical": "口",
    "frequency": 58,
    "pos": [
      "y"
    ],
    "forms": [
      {
        "traditional": "吧",
        "transcriptions": {
          "pinyin": "bā",
          "numeric": "ba1",
          "wadegiles": "pa¹",
          "bopomofo": "ㄅㄚ",
          "romatzyh": "ba"
        },
        "meanings": [
          "bar (loanword) (serving drinks, or providing Internet access etc)",
          "to puff (on a pipe etc)",
          "(onom.) bang",
          "abbr. for 贴吧"
        ],
        "classifiers": []
      },
      {
        "traditional": "吧",
        "transcriptions": {
          "pinyin": "ba",
          "numeric": "ba5",
          "wadegiles": "ba",
          "bopomofo": "ba",
          "romatzyh": "ba"
        },
        "meanings": [
          "(modal particle indicating suggestion or surmise)",
          "...right?",
          "...OK?",
          "...I presume."
        ],
        "classifiers": []
      },
      {
        "traditional": "吧",
        "transcriptions": {
          "pinyin": "biā",
          "numeric": "bia1",
          "wadegiles": "biā",
          "bopomofo": "biā",
          "romatzyh": "biā"
        },
        "meanings": [
          "(onom.) smack!"
        ],
        "classifiers": []
      }
    ]
  },
  {
    "simplified": "白",
    "radical": "白",
    "frequency": 930,
    "pos": [
      "a",
      "nr",
      "d",
      "b",
      "v",
      "g"
    ],
    "forms": [
      {
        "traditional": "白",
        "transcriptions": {
          "pinyin": "Bái",
          "numeric": "Bai2",
          "wadegiles": "pai²",
          "bopomofo": "ㄅㄞˊ",
          "romatzyh": "bair"
        },
        "meanings": [
          "surname Bai"
        ],
        "classifiers": []
      },
      {
        "traditional": "白",
        "transcriptions": {
          "pinyin": "bái",
          "numeric": "bai2",
          "wadegiles": "pai²",
          "bopomofo": "ㄅㄞˊ",
          "romatzyh": "bair"
        },
        "meanings": [
          "white",
          "snowy",
          "pure",
          "bright",
          "empty",
          "blank",
          "plain",
          "clear",
          "to make clear",
          "in vain",
          "gratuitous",
          "free of charge",
          "reactionary",
          "anti-communist",
          "funeral",
          "to stare coldly",
          "to write wrong character",
          "to state",
          "to explain",
          "vernacular",
          "spoken lines in opera"
        ],
        "classifiers": []
      }
    ]
  },
  {
    "simplified": "白天",
    "radical": "白",
    "frequency": 3645,
    "pos": [
      "t"
    ],
    "forms": [
      {
        "traditional": "白天",
        "transcriptions": {
          "pinyin": "bái tiān",
          "numeric": "bai2 tian1",
          "wadegiles": "pai² t'ien¹",
          "bopomofo": "ㄅㄞˊ ㄊㄧㄢ",
          "romatzyh": "bair tian"
        },
        "meanings": [
          "daytime",
          "during the day",
          "day"
        ],
        "classifiers": [
          "个"
        ]
      }
    ]
  },
  {
    "simplified": "百",
    "radical": "白",
    "frequency": 2455,
    "pos": [
      "m",
      "t"
    ],
    "forms": [
      {
        "traditional": "百",
        "transcriptions": {
          "pinyin": "Bǎi",
          "numeric": "Bai3",
          "wadegiles": "pai³",
          "bopomofo": "ㄅㄞˇ",
          "romatzyh": "bae"
        },
        "meanings": [
          "surname Bai"
        ],
        "classifiers": []
      },
      {
        "traditional": "百",
        "transcriptions": {
          "pinyin": "bǎi",
          "numeric": "bai3",
          "wadegiles": "pai³",
          "bopomofo": "ㄅㄞˇ",
          "romatzyh": "bae"
        },
        "meanings": [
          "hundred",
          "numerous",
          "all kinds of"
        ],
        "classifiers": []
      }
    ]
  },
  {
    "simplified": "班",
    "radical": "王",
    "frequency": 1238,
    "pos": [
      "n",
      "q",
      "nr"
    ],
    "forms": [
      {
        "traditional": "班",
        "transcriptions": {
          "pinyin": "Bān",
          "numeric": "Ban1",
          "wadegiles": "pan¹",
          "bopomofo": "ㄅㄢ",
          "romatzyh": "ban"
        },
        "meanings": [
          "surname Ban"
        ],
        "classifiers": []
      },
      {
        "traditional": "班",
        "transcriptions": {
          "pinyin": "bān",
          "numeric": "ban1",
          "wadegiles": "pan¹",
          "bopomofo": "ㄅㄢ",
          "romatzyh": "ban"
        },
        "meanings": [
          "team; class; grade",
          "(military) squad",
          "work shift",
          "classifier for groups of people and scheduled transport vehicles"
        ],
        "classifiers": [
          "个"
        ]
      }
    ]
  },
  {
    "simplified": "半",
    "radical": "十",
    "frequency": 727,
    "pos": [
      "m"
    ],
    "forms": [
      {
        "traditional": "半",
        "transcriptions": {
          "pinyin": "bàn",
          "numeric": "ban4",
          "wadegiles": "pan⁴",
          "bopomofo": "ㄅㄢˋ",
          "romatzyh": "bann"
        },
        "meanings": [
          "half",
          "semi-",
          "incomplete",
          "(after a number) and a half"
        ],
        "classifiers": []
      }
    ]
  },
  {
    "simplified": "半年",
    "radical": "十",
    "frequency": 37795,
    "pos": [
      "nr"
    ],
    "forms": [
      {
        "traditional": "半年",
        "transcriptions": {
          "pinyin": "bàn nián",
          "numeric": "ban4 nian2",
          "wadegiles": "pan⁴ nien²",
          "bopomofo": "ㄅㄢˋ ㄋㄧㄢˊ",
          "romatzyh": "bann nian"
        },
        "meanings": [
          "half a year"
        ],
        "classifiers": []
      }
    ]
  },
  {
    "simplified": "半天",
    "radical": "十",
    "frequency": 7467,
    "pos": [
      "mq",
      "t"
    ],
    "forms": [
      {
        "traditional": "半天",
        "transcriptions": {
          "pinyin": "bàn tiān",
          "numeric": "ban4 tian1",
          "wadegiles": "pan⁴ t'ien¹",
          "bopomofo": "ㄅㄢˋ ㄊㄧㄢ",
          "romatzyh": "bann tian"
        },
        "meanings": [
          "half of the day",
          "a long time",
          "quite a while",
          "midair"
        ],
        "classifiers": [
          "个"
        ]
      }
    ]
  },
  {
    "simplified": "帮",
    "radical": "巾",
    "frequency": 395,
    "pos": [
      "v",
      "q"
    ],
    "forms": [
      {
        "traditional": "幇",
        "transcriptions": {
          "pinyin": "bāng",
          "numeric": "bang1",
          "wadegiles": "pang¹",
          "bopomofo": "ㄅㄤ",
          "romatzyh": "bang"
        },
        "meanings": [
          "old variant of 帮"
        ],
        "classifiers": []
      },
      {
        "traditional": "幚",
        "transcriptions": {
          "pinyin": "bāng",
          "numeric": "bang1",
          "wadegiles": "pang¹",
          "bopomofo": "ㄅㄤ",
          "romatzyh": "bang"
        },
        "meanings": [
          "old variant of 帮"
        ],
        "classifiers": []
      },
      {
        "traditional": "幫",
        "transcriptions": {
          "pinyin": "bāng",
          "numeric": "bang1",
          "wadegiles": "pang¹",
          "bopomofo": "ㄅㄤ",
          "romatzyh": "bang"
        },
        "meanings": [
          "to help",
          "to assist",
          "to support",
          "for sb (i.e. as a help)",
          "hired (as worker)",
          "side (of pail, boat etc)",
          "outer layer",
          "upper (of a shoe)",
          "group",
          "gang",
          "clique",
          "party",
          "secret society"
        ],
        "classifiers": []
      }
    ]
  },
  {
    "simplified": "帮忙",
    "radical": "巾",
    "frequency": 1860,
    "pos": [
      "v",
      "vn"
    ],
    "forms": [
      {
        "traditional": "幫忙",
        "transcriptions": {
          "pinyin": "bāng máng",
          "numeric": "bang1 mang2",
          "wadegiles": "pang¹ mang²",
          "bopomofo": "ㄅㄤ ㄇㄤˊ",
          "romatzyh": "bang mang"
        },
        "meanings": [
          "to help",
          "to lend a hand",
          "to do a favor",
          "to do a good turn"
        ],
        "classifiers": []
      }
    ]
  },
  {
    "simplified": "包",
    "radical": "勹",
    "frequency": 755,
    "pos": [
      "v",
      "n",
      "q"
    ],
    "forms": [
      {
        "traditional": "包",
        "transcriptions": {
          "pinyin": "Bāo",
          "numeric": "Bao1",
          "wadegiles": "pao¹",
          "bopomofo": "ㄅㄠ",
          "romatzyh": "bau"
        },
        "meanings": [
          "surname Bao"
        ],
        "classifiers": []
      },
      {
        "traditional": "包",
        "transcriptions": {
          "pinyin": "bāo",
          "numeric": "bao1",
          "wadegiles": "pao¹",
          "bopomofo": "ㄅㄠ",
          "romatzyh": "bau"
        },
        "meanings": [
          "to cover",
          "to wrap",
          "to hold",
          "to include",
          "to take charge of",
          "to contract (to or for)",
          "package",
          "wrapper",
          "container",
          "bag",
          "to hold or embrace",
          "bundle",
          "packet"
        ],
        "classifiers": [
          "个",
          "只"
        ]
      }
    ]
  },
  {
    "simplified": "包子",
    "radical": "勹",
    "frequency": 16315,
    "pos": [
      "n"
    ],
    "forms": [
      {
        "traditional": "包子",
        "transcriptions": {
          "pinyin": "bāo zi",
          "numeric": "bao1 zi5",
          "wadegiles": "pao¹ zi",
          "bopomofo": "ㄅㄠ zi",
          "romatzyh": "bau zi"
        },
        "meanings": [
          "bao (steamed stuffed bun)"
        ],
        "classifiers": [
          "个"
        ]
      }
    ]
  },
  {
    "simplified": "杯",
    "radical": "木",
    "frequency": 684,
    "pos": [
      "q",
      "g"
    ],
    "forms": [
      {
        "traditional": "杯",
        "transcriptions": {
          "pinyin": "bēi",
          "numeric": "bei1",
          "wadegiles": "pei¹",
          "bopomofo": "ㄅㄟ",
          "romatzyh": "bei"
        },
        "meanings": [
          "cup",
          "trophy cup",
          "classifier for certain containers of liquids: glass, cup"
        ],
        "classifiers": []
      },
      {
        "traditional": "桮",
        "transcriptions": {
          "pinyin": "bēi",
          "numeric": "bei1",
          "wadegiles": "pei¹",
          "bopomofo": "ㄅㄟ",
          "romatzyh": "bei"
        },
        "meanings": [
          "variant of 杯"
        ],
        "classifiers": []
      },
      {
        "traditional": "盃",
        "transcriptions": {
          "pinyin": "bēi",
          "numeric": "bei1",
          "wadegiles": "pei¹",
          "bopomofo": "ㄅㄟ",
          "romatzyh": "bei"
        },
        "meanings": [
          "variant of 杯",
          "trophy cup",
          "classifier for certain containers of liquids: glass, cup"
        ],
        "classifiers": []
      }
    ]
  },
  {
    "simplified": "杯子",
    "radical": "木",
    "frequency": 6162,
    "pos": [
      "n"
    ],
    "forms": [
      {
        "traditional": "杯子",
        "transcriptions": {
          "pinyin": "bēi zi",
          "numeric": "bei1 zi5",
          "wadegiles": "pei¹ zi",
          "bopomofo": "ㄅㄟ zi",
          "romatzyh": "bei zi"
        },
        "meanings": [
          "cup",
          "glass"
        ],
        "classifiers": [
          "个",
          "只"
        ]
      }
    ]
  },
  {
    "simplified": "北",
    "radical": "匕",
    "frequency": 1835,
    "pos": [
      "f"
    ],
    "forms": [
      {
        "traditional": "北",
        "transcriptions": {
          "pinyin": "běi",
          "numeric": "bei3",
          "wadegiles": "pei³",
          "bopomofo": "ㄅㄟˇ",
          "romatzyh": "beei"
        },
        "meanings": [
          "north",
          "(classical) to be defeated"
        ],
        "classifiers": []
      }
    ]
  },
  {
    "simplified": "北边",
    "radical": "匕",
    "frequency": 17637,
    "pos": [
      "f"
    ],
    "forms": [
      {
        "traditional": "北邊",
        "transcriptions": {
          "pinyin": "běi biān",
          "numeric": "bei3 bian1",
          "wadegiles": "pei³ pien¹",
          "bopomofo": "ㄅㄟˇ ㄅㄧㄢ",
          "romatzyh": "beei bian"
        },
        "meanings": [
          "north",
          "north side",
          "northern part",
          "to the north of"
        ],
        "classifiers": []
      }
    ]
  },
  {
    "simplified": "北京",
    "radical": "匕",
    "frequency": 4799,
    "pos": [
      "ns"
    ],
    "forms": [
      {
        "traditional": "北京",
        "transcriptions": {
          "pinyin": "Běi jīng",
          "numeric": "Bei3 jing1",
          "wadegiles": "pei³ ching¹",
          "bopomofo": "ㄅㄟˇ ㄐㄧㄥ",
          "romatzyh": "beei jing"
        },
        "meanings": [
          "Beijing, capital of the People's Republic of China"
        ],
        "classifiers": []
      }
    ]
  },
  {
    "simplified": "本",
    "radical": "木",
    "frequency": 222,
    "pos": [
      "r",
      "q",
      "d",
      "n"
    ],
    "forms": [
      {
        "traditional": "本",
        "transcriptions": {
          "pinyin": "běn",
          "numeric": "ben3",
          "wadegiles": "pen³",
          "bopomofo": "ㄅㄣˇ",
          "romatzyh": "been"
        },
        "meanings": [
          "root",
          "stem",
          "origin",
          "source",
          "this",
          "the current",
          "original",
          "inherent",
          "originally",
          "classifier for books, periodicals, files etc"
        ],
        "classifiers": []
      }
    ]
  },
  {
    "simplified": "本子",
    "radical": "木",
    "frequency": 12849,
    "pos": [
      "n"
    ],
    "forms": [
      {
        "traditional": "本子",
        "transcriptions": {
          "pinyin": "běn zi",
          "numeric": "ben3 zi5",
          "wadegiles": "pen³ zi",
          "bopomofo": "ㄅㄣˇ zi",
          "romatzyh": "been zi"
        },
        "meanings": [
          "book",
          "notebook",
          "Japanese-style self-published comic (esp. an erotic one), aka \"dōjinshi\"",
          "edition"
        ],
        "classifiers": [
          "本"
        ]
      }
    ]
  },
  {
    "simplified": "比",
    "radical": "比",
    "frequency": 155,
    "pos": [
      "p",
      "v",
      "n",
      "b"
    ],
    "forms": [
      {
        "traditional": "比",
        "transcriptions": {
          "pinyin": "Bǐ",
          "numeric": "Bi3",
          "wadegiles": "pi³",
          "bopomofo": "ㄅㄧˇ",
          "romatzyh": "bii"
        },
        "meanings": [
          "Belgium",
          "Belgian",
          "abbr. for 比利时"
        ],
        "classifiers": []
      },
      {
        "traditional": "比",
        "transcriptions": {
          "pinyin": "bī",
          "numeric": "bi1",
          "wadegiles": "pi¹",
          "bopomofo": "ㄅㄧ",
          "romatzyh": "bi"
        },
        "meanings": [
          "euphemistic variant of 屄"
        ],
        "classifiers": []
      },
      {
        "traditional": "比",
        "transcriptions": {
          "pinyin": "bǐ",
          "numeric": "bi3",
          "wadegiles": "pi³",
          "bopomofo": "ㄅㄧˇ",
          "romatzyh": "bii"
        },
        "meanings": [
          "to compare",
          "(followed by a noun and adjective) more {adj.} than {noun}",
          "ratio",
          "to gesture",
          "(Taiwan pr. [bì] in some compounds derived from Classical Chinese)"
        ],
        "classifiers": []
      }
    ]
  },
  {
    "simplified": "别",
    "radical": "刂",
    "frequency": 214,
    "pos": [
      "d",
      "v",
      "r",
      "vn"
    ],
    "forms": [
      {
        "traditional": "別",
        "transcriptions": {
          "pinyin": "Bié",
          "numeric": "Bie2",
          "wadegiles": "pieh²",
          "bopomofo": "ㄅㄧㄝˊ",
          "romatzyh": "bye"
        },
        "meanings": [
          "surname Bie"
        ],
        "classifiers": []
      },
      {
        "traditional": "別",
        "transcriptions": {
          "pinyin": "bié",
          "numeric": "bie2",
          "wadegiles": "pieh²",
          "bopomofo": "ㄅㄧㄝˊ",
          "romatzyh": "bye"
        },
        "meanings": [
          "to leave; to part (from)",
          "(literary) to differentiate; to distinguish",
          "(bound form) other; another; different",
          "don't ...!",
          "to fasten with a pin or clip",
          "to stick in; to insert (in order to hinder movement)",
          "(noun suffix) category (e.g. 性别, 派别)"
        ],
        "classifiers": []
      },
      {
        "traditional": "彆",
        "transcriptions": {
          "pinyin": "biè",
          "numeric": "bie4",
          "wadegiles": "pieh⁴",
          "bopomofo": "ㄅㄧㄝˋ",
          "romatzyh": "bieh"
        },
        "meanings": [
          "to make sb change their ways, opinions etc"
        ],
        "classifiers": []
      }
    ]
  },
  {
    "simplified": "别的",
    "radical": "刂",
    "frequency": 543,
    "pos": [
      "r"
    ],
    "forms": [
      {
        "traditional": "別的",
        "transcriptions": {
          "pinyin": "bié de",
          "numeric": "bie2 de5",
          "wadegiles": "pieh² de",
          "bopomofo": "ㄅㄧㄝˊ de",
          "romatzyh": "bye de"
        },
        "meanings": [
          "else",
          "other"
        ],
        "classifiers": []
      }
    ]
  },
  {
    "simplified": "别人",
    "radical": "刂",
    "frequency": 397,
    "pos": [
      "r"
    ],
    "forms": [
      {
        "traditional": "別人",
        "transcriptions": {
          "pinyin": "bié ren",
          "numeric": "bie2 ren5",
          "wadegiles": "pieh² ren",
          "bopomofo": "ㄅㄧㄝˊ ren",
          "romatzyh": "bye ren"
        },
        "meanings": [
          "other people; others; other person"
        ],
        "classifiers": []
      }
    ]
  },
  {
    "simplified": "病",
    "radical": "疒",
    "frequency": 827,
    "pos": [
      "n",
      "v"
    ],
    "forms": [
      {
        "traditional": "病",
        "transcriptions": {
          "pinyin": "bìng",
          "numeric": "bing4",
          "wadegiles": "ping⁴",
          "bopomofo": "ㄅㄧㄥˋ",
          "romatzyh": "binq"
        },
        "meanings": [
          "illness",
          "disease",
          "to fall ill",
          "defect"
        ],
        "classifiers": [
          "场"
        ]
      }
    ]
  },
  {
    "simplified": "病人",
    "radical": "疒",
    "frequency": 1209,
    "pos": [
      "n"
    ],
    "forms": [
      {
        "traditional": "病人",
        "transcriptions": {
          "pinyin": "bìng rén",
          "numeric": "bing4 ren2",
          "wadegiles": "ping⁴ jen²",
          "bopomofo": "ㄅㄧㄥˋ ㄖㄣˊ",
          "romatzyh": "binq ren"
        },
        "meanings": [
          "sick person",
          "patient",
          "invalid"
        ],
        "classifiers": [
          "个"
        ]
      }
    ]
  },
  {
    "simplified": "不",
    "radical": "一",
    "frequency": 9,
    "pos": [
      "d"
    ],
    "forms": [
      {
        "traditional": "不",
        "transcriptions": {
          "pinyin": "bù",
          "numeric": "bu4",
          "wadegiles": "pu⁴",
          "bopomofo": "ㄅㄨˋ",
          "romatzyh": "buh"
        },
        "meanings": [
          "no; not so",
          "(bound form) not; un-"
        ],
        "classifiers": []
      }
    ]
  },
  {
    "simplified": "不大",
    "radical": "一",
    "frequency": 4915,
    "pos": [
      "d"
    ],
    "forms": [
      {
        "traditional": "不大",
        "transcriptions": {
          "pinyin": "bù dà",
          "numeric": "bu4 da4",
          "wadegiles": "pu⁴ ta⁴",
          "bopomofo": "ㄅㄨˋ ㄉㄚˋ",
          "romatzyh": "buh dah"
        },
        "meanings": [
          "not very",
          "not too",
          "not often"
        ],
        "classifiers": []
      }
    ]
  },
  {
    "simplified": "不对",
    "radical": "一",
    "frequency": 2598,
    "pos": [
      "a"
    ],
    "forms": [
      {
        "traditional": "不對",
        "transcriptions": {
          "pinyin": "bù duì",
          "numeric": "bu4 dui4",
          "wadegiles": "pu⁴ tui⁴",
          "bopomofo": "ㄅㄨˋ ㄉㄨㄟˋ",
          "romatzyh": "buh duey"
        },
        "meanings": [
          "incorrect",
          "wrong",
          "amiss",
          "abnormal",
          "queer"
        ],
        "classifiers": []
      }
    ]
  },
  {
    "simplified": "不客气",
    "radical": "一",
    "frequency": 16723,
    "pos": [],
    "forms": [
      {
        "traditional": "不客氣",
        "transcriptions": {
          "pinyin": "bù kè qi",
          "numeric": "bu4 ke4 qi5",
          "wadegiles": "pu⁴ k'o⁴ qi",
          "bopomofo": "ㄅㄨˋ ㄎㄜˋ qi",
          "romatzyh": "buh keh qi"
        },
        "meanings": [
          "you're welcome",
          "don't mention it",
          "impolite",
          "rude",
          "blunt"
        ],
        "classifiers": []
      }
    ]
  },
  {
    "simplified": "不用",
    "radical": "一",
    "frequency": 1013,
    "pos": [
      "d"
    ],
    "forms": [
      {
        "traditional": "不用",
        "transcriptions": {
          "pinyin": "bù yòng",
          "numeric": "bu4 yong4",
          "wadegiles": "pu⁴ yung⁴",
          "bopomofo": "ㄅㄨˋ ㄩㄥˋ",
          "romatzyh": "buh yonq"
        },
        "meanings": [
          "need not"
        ],
        "classifiers": []
      }
    ]
  },
  {
    "simplified": "菜",
    "radical": "艹",
    "frequency": 1448,
    "pos": [
      "n"
    ],
    "forms": [
      {
        "traditional": "菜",
        "transcriptions": {
          "pinyin": "cài",
          "numeric": "cai4",
          "wadegiles": "ts'ai⁴",
          "bopomofo": "ㄘㄞˋ",
          "romatzyh": "tsay"
        },
        "meanings": [
          "dish (type of food)",
          "vegetable",
          "cuisine",
          "(coll.) (one's) type",
          "(of one's skills etc) weak",
          "poor"
        ],
        "classifiers": [
          "盘",
          "道"
        ]
      }
    ]
  },
  {
    "simplified": "茶",
    "radical": "艹",
    "frequency": 1910,
    "pos": [
      "n",
      "g"
    ],
    "forms": [
      {
        "traditional": "茶",
        "transcriptions": {
          "pinyin": "chá",
          "numeric": "cha2",
          "wadegiles": "ch'a²",
          "bopomofo": "ㄔㄚˊ",
          "romatzyh": "char"
        },
        "meanings": [
          "tea",
          "tea plant"
        ],
        "classifiers": [
          "杯",
          "壶"
        ]
      }
    ]
  },
  {
    "simplified": "差",
    "radical": "工",
    "frequency": 968,
    "pos": [
      "a",
      "v",
      "g"
    ],
    "forms": [
      {
        "traditional": "差",
        "transcriptions": {
          "pinyin": "chā",
          "numeric": "cha1",
          "wadegiles": "ch'a¹",
          "bopomofo": "ㄔㄚ",
          "romatzyh": "cha"
        },
        "meanings": [
          "difference; discrepancy",
          "(math.) difference (amount remaining after a subtraction)",
          "(literary) a little; somewhat; slightly"
        ],
        "classifiers": []
      },
      {
        "traditional": "差",
        "transcriptions": {
          "pinyin": "chà",
          "numeric": "cha4",
          "wadegiles": "ch'a⁴",
          "bopomofo": "ㄔㄚˋ",
          "romatzyh": "chah"
        },
        "meanings": [
          "different",
          "wrong; mistaken",
          "to fall short; to lack",
          "not up to standard; inferior",
          "Taiwan pr. [chā]"
        ],
        "classifiers": []
      },
      {
        "traditional": "差",
        "transcriptions": {
          "pinyin": "chāi",
          "numeric": "chai1",
          "wadegiles": "ch'ai¹",
          "bopomofo": "ㄔㄞ",
          "romatzyh": "chai"
        },
        "meanings": [
          "to send (on an errand)",
          "(archaic) person sent on such an errand",
          "job; official post"
        ],
        "classifiers": []
      },
      {
        "traditional": "差",
        "transcriptions": {
          "pinyin": "cī",
          "numeric": "ci1",
          "wadegiles": "tz'u¹",
          "bopomofo": "ㄘ",
          "romatzyh": "tsy"
        },
        "meanings": [
          "used in 参差"
        ],
        "classifiers": []
      }
    ]
  },
  {
    "simplified": "常",
    "radical": "巾",
    "frequency": 1057,
    "pos": [
      "d",
      "nr"
    ],
    "forms": [
      {
        "traditional": "常",
        "transcriptions": {
          "pinyin": "Cháng",
          "numeric": "Chang2",
          "wadegiles": "ch'ang²",
          "bopomofo": "ㄔㄤˊ",
          "romatzyh": "charng"
        },
        "meanings": [
          "surname Chang"
        ],
        "classifiers": []
      },
      {
        "traditional": "常",
        "transcriptions": {
          "pinyin": "cháng",
          "numeric": "chang2",
          "wadegiles": "ch'ang²",
          "bopomofo": "ㄔㄤˊ",
          "romatzyh": "charng"
        },
        "meanings": [
          "always",
          "ever",
          "often",
          "frequently",
          "common",
          "general",
          "constant"
        ],
        "classifiers": []
      }
    ]
  },
  {
    "simplified": "常常",
    "radical": "巾",
    "frequency": 2773,
    "pos": [
      "d"
    ],
    "forms": [
      {
        "traditional": "常常",
        "transcriptions": {
          "pinyin": "cháng cháng",
          "numeric": "chang2 chang2",
          "wadegiles": "ch'ang² ch'ang²",
          "bopomofo": "ㄔㄤˊ ㄔㄤˊ",
          "romatzyh": "charng charng"
        },
        "meanings": [
          "frequently",
          "often"
        ],
        "classifiers": []
      }
    ]
  },
  {
    "simplified": "唱",
    "radical": "口",
    "frequency": 813,
    "pos": [
      "v"
    ],
    "forms": [
      {
        "traditional": "唱",
        "transcriptions": {
          "pinyin": "chàng",
          "numeric": "chang4",
          "wadegiles": "ch'ang⁴",
          "bopomofo": "ㄔㄤˋ",
          "romatzyh": "chanq"
        },
        "meanings": [
          "to sing",
          "to call loudly",
          "to chant"
        ],
        "classifiers": []
      }
    ]
  },
  {
    "simplified": "唱歌",
    "radical": "口",
    "frequency": 2876,
    "pos": [
      "v",
      "vn"
    ],
    "forms": [
      {
        "traditional": "唱歌",
        "transcriptions": {
          "pinyin": "chàng gē",
          "numeric": "chang4 ge1",
          "wadegiles": "ch'ang⁴ ko¹",
          "bopomofo": "ㄔㄤˋ ㄍㄜ",
          "romatzyh": "chanq ge"
        },
        "meanings": [
          "to sing a song"
        ],
        "classifiers": []
      }
    ]
  },
  {
    "simplified": "车",
    "radical": "车",
    "frequency": 186,
    "pos": [
      "n",
      "q"
    ],
    "forms": [
      {
        "traditional": "車",
        "transcriptions": {
          "pinyin": "Chē",
          "numeric": "Che1",
          "wadegiles": "ch'e¹",
          "bopomofo": "ㄔㄜ",
          "romatzyh": "che"
        },
        "meanings": [
          "surname Che"
        ],
        "classifiers": []
      },
      {
        "traditional": "車",
        "transcriptions": {
          "pinyin": "chē",
          "numeric": "che1",
          "wadegiles": "ch'e¹",
          "bopomofo": "ㄔㄜ",
          "romatzyh": "che"
        },
        "meanings": [
          "car",
          "vehicle",
          "machine",
          "to shape with a lathe",
          "Kangxi radical 159"
        ],
        "classifiers": [
          "辆"
        ]
      },
      {
        "traditional": "車",
        "transcriptions": {
          "pinyin": "jū",
          "numeric": "ju1",
          "wadegiles": "chü¹",
          "bopomofo": "ㄐㄩ",
          "romatzyh": "jiu"
        },
        "meanings": [
          "war chariot (archaic)",
          "rook (in Chinese chess)",
          "rook (in chess)"
        ],
        "classifiers": []
      }
    ]
  },
  {
    "simplified": "车票",
    "radical": "车",
    "frequency": 7701,
    "pos": [
      "n"
    ],
    "forms": [
      {
        "traditional": "車票",
        "transcriptions": {
          "pinyin": "chē piào",
          "numeric": "che1 piao4",
          "wadegiles": "ch'e¹ p'iao⁴",
          "bopomofo": "ㄔㄜ ㄆㄧㄠˋ",
          "romatzyh": "che piaw"
        },
        "meanings": [
          "ticket (for a bus or train)"
        ],
        "classifiers": []
      }
    ]
  },
  {
    "simplified": "车上",
    "radical": "车",
    "frequency": 1997,
    "pos": [
      "s"
    ],
    "forms": [
      {
        "traditional": "車上",
        "transcriptions": {
          "pinyin": "chē shàng",
          "numeric": "che1 shang4",
          "wadegiles": "ch'e¹ shang⁴",
          "bopomofo": "ㄔㄜ ㄕㄤˋ",
          "romatzyh": "che shanq"
        },
        "meanings": [
          "Car"
        ],
        "classifiers": []
      }
    ]
  },
  {
    "simplified": "车站",
    "radical": "车",
    "frequency": 4480,
    "pos": [
      "n"
    ],
    "forms": [
      {
        "traditional": "車站",
        "transcriptions": {
          "pinyin": "chē zhàn",
          "numeric": "che1 zhan4",
          "wadegiles": "ch'e¹ chan⁴",
          "bopomofo": "ㄔㄜ ㄓㄢˋ",
          "romatzyh": "che jann"
        },
        "meanings": [
          "rail station",
          "bus stop"
        ],
        "classifiers": [
          "处",
          "个"
        ]
      }
    ]
  },
  {
    "simplified": "吃",
    "radical": "口",
    "frequency": 142,
    "pos": [
      "v"
    ],
    "forms": [
      {
        "traditional": "吃",
        "transcriptions": {
          "pinyin": "chī",
          "numeric": "chi1",
          "wadegiles": "ch'ih¹",
          "bopomofo": "ㄔ",
          "romatzyh": "chy"
        },
        "meanings": [
          "to eat; to consume",
          "to eat at (a cafeteria etc)",
          "to eradicate; to destroy",
          "to absorb",
          "to suffer (shock, injury, defeat etc)"
        ],
        "classifiers": []
      },
      {
        "traditional": "喫",
        "transcriptions": {
          "pinyin": "chī",
          "numeric": "chi1",
          "wadegiles": "ch'ih¹",
          "bopomofo": "ㄔ",
          "romatzyh": "chy"
        },
        "meanings": [
          "variant of 吃"
        ],
        "classifiers": []
      }
    ]
  },
  {
    "simplified": "吃饭",
    "radical": "口",
    "frequency": 1415,
    "pos": [
      "v",
      "vn"
    ],
    "forms": [
      {
        "traditional": "吃飯",
        "transcriptions": {
          "pinyin": "chī fàn",
          "numeric": "chi1 fan4",
          "wadegiles": "ch'ih¹ fan⁴",
          "bopomofo": "ㄔ ㄈㄢˋ",
          "romatzyh": "chy fann"
        },
        "meanings": [
          "to have a meal",
          "to eat",
          "to make a living"
        ],
        "classifiers": []
      }
    ]
  },
  {
    "simplified": "出",
    "radical": "凵",
    "frequency": 85,
    "pos": [
      "v",
      "q"
    ],
    "forms": [
      {
        "traditional": "出",
        "transcriptions": {
          "pinyin": "chū",
          "numeric": "chu1",
          "wadegiles": "ch'u¹",
          "bopomofo": "ㄔㄨ",
          "romatzyh": "chu"
        },
        "meanings": [
          "to go out",
          "to come out",
          "to occur",
          "to produce",
          "to go beyond",
          "to rise",
          "to put forth",
          "to happen",
          "(used after a verb to indicate an outward direction or a positive result)",
          "classifier for dramas, plays, operas etc"
        ],
        "classifiers": []
      },
      {
        "traditional": "齣",
        "transcriptions": {
          "pinyin": "chū",
          "numeric": "chu1",
          "wadegiles": "ch'u¹",
          "bopomofo": "ㄔㄨ",
          "romatzyh": "chu"
        },
        "meanings": [
          "variant of 出 (classifier for plays or chapters of classical novels)"
        ],
        "classifiers": []
      }
    ]
  },
  {
    "simplified": "出来",
    "radical": "凵",
    "frequency": 254,
    "pos": [
      "v"
    ],
    "forms": [
      {
        "traditional": "出來",
        "transcriptions": {
          "pinyin": "chū lái",
          "numeric": "chu1 lai2",
          "wadegiles": "ch'u¹ lai²",
          "bopomofo": "ㄔㄨ ㄌㄞˊ",
          "romatzyh": "chu lai"
        },
        "meanings": [
          "to come out",
          "to appear",
          "to arise"
        ],
        "classifiers": []
      },
      {
        "traditional": "出來",
        "transcriptions": {
          "pinyin": "chu lai",
          "numeric": "chu5 lai5",
          "wadegiles": "chu lai",
          "bopomofo": "chu lai",
          "romatzyh": "chu lai"
        },
        "meanings": [
          "(after a verb, indicates coming out, completion of an action, or ability to discern or detect)"
        ],
        "classifiers": []
      }
    ]
  },
  {
    "simplified": "出去",
    "radical": "凵",
    "frequency": 784,
    "pos": [
      "v"
    ],
    "forms": [
      {
        "traditional": "出去",
        "transcriptions": {
          "pinyin": "chū qù",
          "numeric": "chu1 qu4",
          "wadegiles": "ch'u¹ ch'ü⁴",
          "bopomofo": "ㄔㄨ ㄑㄩˋ",
          "romatzyh": "chu chiuh"
        },
        "meanings": [
          "to go out"
        ],
        "classifiers": []
      }
    ]
  },
  {
    "simplified": "穿",
    "radical": "穴",
    "frequency": 430,
    "pos": [
      "v"
    ],
    "forms": [
      {
        "traditional": "穿",
        "transcriptions": {
          "pinyin": "chuān",
          "numeric": "chuan1",
          "wadegiles": "ch'uan¹",
          "bopomofo": "ㄔㄨㄢ",
          "romatzyh": "chuan"
        },
        "meanings": [
          "to wear",
          "to put on",
          "to dress",
          "to bore through",
          "to pierce",
          "to perforate",
          "to penetrate",
          "to pass through",
          "to thread"
        ],
        "classifiers": []
      }
    ]
  },
  {
    "simplified": "床",
    "radical": "广",
    "frequency": 961,
    "pos": [
      "n",
      "q"
    ],
    "forms": [
      {
        "traditional": "床",
        "transcriptions": {
          "pinyin": "chuáng",
          "numeric": "chuang2",
          "wadegiles": "ch'uang²",
          "bopomofo": "ㄔㄨㄤˊ",
          "romatzyh": "chwang"
        },
        "meanings": [
          "bed",
          "couch",
          "classifier for beds"
        ],
        "classifiers": [
          "张"
        ]
      },
      {
        "traditional": "牀",
        "transcriptions": {
          "pinyin": "chuáng",
          "numeric": "chuang2",
          "wadegiles": "ch'uang²",
          "bopomofo": "ㄔㄨㄤˊ",
          "romatzyh": "chwang"
        },
        "meanings": [
          "variant of 床"
        ],
        "classifiers": []
      }
    ]
  },
  {
    "simplified": "次",
    "radical": "欠",
    "frequency": 99,
    "pos": [
      "qv",
      "a",
      "g"
    ],
    "forms": [
      {
        "traditional": "次",
        "transcriptions": {
          "pinyin": "cì",
          "numeric": "ci4",
          "wadegiles": "tz'u⁴",
          "bopomofo": "ㄘˋ",
          "romatzyh": "tsyh"
        },
        "meanings": [
          "next in sequence",
          "second",
          "the second (day, time etc)",
          "secondary",
          "vice-",
          "sub-",
          "infra-",
          "inferior quality",
          "substandard",
          "order",
          "sequence",
          "hypo- (chemistry)",
          "classifier for enumerated events: time"
        ],
        "classifiers": []
      }
    ]
  },
  {
    "simplified": "从",
    "radical": "人",
    "frequency": 70,
    "pos": [
      "p",
      "g"
    ],
    "forms": [
      {
        "traditional": "从",
        "transcriptions": {
          "pinyin": "cóng",
          "numeric": "cong2",
          "wadegiles": "ts'ung²",
          "bopomofo": "ㄘㄨㄥˊ",
          "romatzyh": "tsorng"
        },
        "meanings": [
          "variant of 从"
        ],
        "classifiers": []
      },
      {
        "traditional": "從",
        "transcriptions": {
          "pinyin": "Cóng",
          "numeric": "Cong2",
          "wadegiles": "ts'ung²",
          "bopomofo": "ㄘㄨㄥˊ",
          "romatzyh": "tsorng"
        },
        "meanings": [
          "surname Cong"
        ],
        "classifiers": []
      },
      {
        "traditional": "從",
        "transcriptions": {
          "pinyin": "cóng",
          "numeric": "cong2",
          "wadegiles": "ts'ung²",
          "bopomofo": "ㄘㄨㄥˊ",
          "romatzyh": "tsorng"
        },
        "meanings": [
          "from",
          "through",
          "via",
          "to follow",
          "to obey",
          "to engage in (an activity)",
          "never (in negative sentence)",
          "(Taiwan pr. [zòng]) retainer",
          "assistant",
          "auxiliary",
          "subordinate",
          "related by common paternal grandfather or earlier ancestor"
        ],
        "classifiers": []
      }
    ]
  },
  {
    "simplified": "错",
    "radical": "钅",
    "frequency": 531,
    "pos": [
      "v",
      "n"
    ],
    "forms": [
      {
        "traditional": "錯",
        "transcriptions": {
          "pinyin": "Cuò",
          "numeric": "Cuo4",
          "wadegiles": "ts'o⁴",
          "bopomofo": "ㄘㄨㄛˋ",
          "romatzyh": "tsuoh"
        },
        "meanings": [
          "surname Cuo"
        ],
        "classifiers": []
      },
      {
        "traditional": "錯",
        "transcriptions": {
          "pinyin": "cuò",
          "numeric": "cuo4",
          "wadegiles": "ts'o⁴",
          "bopomofo": "ㄘㄨㄛˋ",
          "romatzyh": "tsuoh"
        },
        "meanings": [
          "mistake",
          "wrong",
          "bad",
          "interlocking",
          "complex",
          "to grind",
          "to polish",
          "to alternate",
          "to stagger",
          "to miss",
          "to let slip",
          "to evade",
          "to inlay with gold or silver"
        ],
        "classifiers": []
      }
    ]
  },
  {
    "simplified": "打",
    "radical": "扌",
    "frequency": 153,
    "pos": [
      "v"
    ],
    "forms": [
      {
        "traditional": "打",
        "transcriptions": {
          "pinyin": "dá",
          "numeric": "da2",
          "wadegiles": "ta²",
          "bopomofo": "ㄉㄚˊ",
          "romatzyh": "dar"
        },
        "meanings": [
          "dozen (loanword)"
        ],
        "classifiers": []
      },
      {
        "traditional": "打",
        "transcriptions": {
          "pinyin": "dǎ",
          "numeric": "da3",
          "wadegiles": "ta³",
          "bopomofo": "ㄉㄚˇ",
          "romatzyh": "daa"
        },
        "meanings": [
          "to beat",
          "to strike",
          "to hit",
          "to break",
          "to type",
          "to mix up",
          "to build",
          "to fight",
          "to fetch",
          "to make",
          "to tie up",
          "to issue",
          "to shoot",
          "to calculate",
          "to play (a game)",
          "since",
          "from"
        ],
        "classifiers": []
      }
    ]
  },
  {
    "simplified": "打车",
    "radical": "扌",
    "frequency": 15698,
    "pos": [
      "v"
    ],
    "forms": [
      {
        "traditional": "打車",
        "transcriptions": {
          "pinyin": "dǎ chē",
          "numeric": "da3 che1",
          "wadegiles": "ta³ ch'e¹",
          "bopomofo": "ㄉㄚˇ ㄔㄜ",
          "romatzyh": "daa che"
        },
        "meanings": [
          "to take a taxi (in town)",
          "to hitch a lift"
        ],
        "classifiers": []
      }
    ]
  },
  {
    "simplified": "打电话",
    "radical": "扌",
    "frequency": 1218,
    "pos": [
      "v"
    ],
    "forms": [
      {
        "traditional": "打電話",
        "transcriptions": {
          "pinyin": "dǎ diàn huà",
          "numeric": "da3 dian4 hua4",
          "wadegiles": "ta³ tien⁴ hua⁴",
          "bopomofo": "ㄉㄚˇ ㄉㄧㄢˋ ㄏㄨㄚˋ",
          "romatzyh": "daa diann huah"
        },
        "meanings": [
          "to make a telephone call"
        ],
        "classifiers": []
      }
    ]
  },
  {
    "simplified": "打开",
    "radical": "扌",
    "frequency": 1199,
    "pos": [
      "v"
    ],
    "forms": [
      {
        "traditional": "打開",
        "transcriptions": {
          "pinyin": "dǎ kāi",
          "numeric": "da3 kai1",
          "wadegiles": "ta³ k'ai¹",
          "bopomofo": "ㄉㄚˇ ㄎㄞ",
          "romatzyh": "daa kai"
        },
        "meanings": [
          "to open",
          "to show (a ticket)",
          "to turn on",
          "to switch on"
        ],
        "classifiers": []
      }
    ]
  },
  {
    "simplified": "打球",
    "radical": "扌",
    "frequency": 5476,
    "pos": [
      "v",
      "vn"
    ],
    "forms": [
      {
        "traditional": "打球",
        "transcriptions": {
          "pinyin": "dǎ qiú",
          "numeric": "da3 qiu2",
          "wadegiles": "ta³ ch'iu²",
          "bopomofo": "ㄉㄚˇ ㄑㄧㄡˊ",
          "romatzyh": "daa chyou"
        },
        "meanings": [
          "to play ball",
          "to play with a ball"
        ],
        "classifiers": []
      }
    ]
  },
  {
    "simplified": "大",
    "radical": "大",
    "frequency": 66,
    "pos": [
      "a",
      "d",
      "n",
      "g"
    ],
    "forms": [
      {
        "traditional": "大",
        "transcriptions": {
          "pinyin": "dà",
          "numeric": "da4",
          "wadegiles": "ta⁴",
          "bopomofo": "ㄉㄚˋ",
          "romatzyh": "dah"
        },
        "meanings": [
          "big; large; great",
          "older (than another person)",
          "eldest (as in 姐)",
          "greatly; freely; fully",
          "(dialect) father",
          "(dialect) uncle (father's brother)"
        ],
        "classifiers": []
      },
      {
        "traditional": "大",
        "transcriptions": {
          "pinyin": "dài",
          "numeric": "dai4",
          "wadegiles": "tai⁴",
          "bopomofo": "ㄉㄞˋ",
          "romatzyh": "day"
        },
        "meanings": [
          "see 夫"
        ],
        "classifiers": []
      }
    ]
  },
  {
    "simplified": "大学",
    "radical": "大",
    "frequency": 814,
    "pos": [
      "n"
    ],
    "forms": [
      {
        "traditional": "大學",
        "transcriptions": {
          "pinyin": "Dà xué",
          "numeric": "Da4 xue2",
          "wadegiles": "ta⁴ hsüeh²",
          "bopomofo": "ㄉㄚˋ ㄒㄩㄝˊ",
          "romatzyh": "dah shyue"
        },
        "meanings": [
          "the Great Learning, one of the Four Books 四书 in Confucianism"
        ],
        "classifiers": []
      },
      {
        "traditional": "大學",
        "transcriptions": {
          "pinyin": "dà xué",
          "numeric": "da4 xue2",
          "wadegiles": "ta⁴ hsüeh²",
          "bopomofo": "ㄉㄚˋ ㄒㄩㄝˊ",
          "romatzyh": "dah shyue"
        },
        "meanings": [
          "university",
          "college"
        ],
        "classifiers": [
          "所"
        ]
      }
    ]
  },
  {
    "simplified": "大学生",
    "radical": "大",
    "frequency": 4422,
    "pos": [
      "n"
    ],
    "forms": [
      {
        "traditional": "大學生",
        "transcriptions": {
          "pinyin": "dà xué shēng",
          "numeric": "da4 xue2 sheng1",
          "wadegiles": "ta⁴ hsüeh² sheng¹",
          "bopomofo": "ㄉㄚˋ ㄒㄩㄝˊ ㄕㄥ",
          "romatzyh": "dah shyue sheng"
        },
        "meanings": [
          "university student",
          "college student"
        ],
        "classifiers": []
      }
    ]
  },
  {
    "simplified": "到",
    "radical": "刂",
    "frequency": 29,
    "pos": [
      "v",
      "p"
    ],
    "forms": [
      {
        "traditional": "到",
        "transcriptions": {
          "pinyin": "dào",
          "numeric": "dao4",
          "wadegiles": "tao⁴",
          "bopomofo": "ㄉㄠˋ",
          "romatzyh": "daw"
        },
        "meanings": [
          "to reach; to arrive",
          "to leave for; to go to",
          "to (a place); until (a time); up to (a point)",
          "(verb complement indicating arriving at a place or reaching a point)",
          "considerate; thoughtful; thorough"
        ],
        "classifiers": []
      }
    ]
  },
  {
    "simplified": "地",
    "radical": "土",
    "frequency": 132,
    "pos": [
      "u",
      "n"
    ],
    "forms": [
      {
        "traditional": "地",
        "transcriptions": {
          "pinyin": "de",
          "numeric": "de5",
          "wadegiles": "de",
          "bopomofo": "de",
          "romatzyh": "de"
        },
        "meanings": [
          "-ly",
          "structural particle: used before a verb or adjective, linking it to preceding modifying adverbial adjunct"
        ],
        "classifiers": []
      },
      {
        "traditional": "地",
        "transcriptions": {
          "pinyin": "dì",
          "numeric": "di4",
          "wadegiles": "ti⁴",
          "bopomofo": "ㄉㄧˋ",
          "romatzyh": "dih"
        },
        "meanings": [
          "earth",
          "ground",
          "field",
          "place",
          "land"
        ],
        "classifiers": [
          "片"
        ]
      }
    ]
  },
  {
    "simplified": "地点",
    "radical": "土",
    "frequency": 1921,
    "pos": [
      "n"
    ],
    "forms": [
      {
        "traditional": "地點",
        "transcriptions": {
          "pinyin": "dì diǎn",
          "numeric": "di4 dian3",
          "wadegiles": "ti⁴ tien³",
          "bopomofo": "ㄉㄧˋ ㄉㄧㄢˇ",
          "romatzyh": "dih dean"
        },
        "meanings": [
          "place",
          "site",
          "location",
          "venue"
        ],
        "classifiers": [
          "个"
        ]
      }
    ]
  },
  {
    "simplified": "地方",
    "radical": "土",
    "frequency": 254,
    "pos": [
      "n"
    ],
    "forms": [
      {
        "traditional": "地方",
        "transcriptions": {
          "pinyin": "dì fāng",
          "numeric": "di4 fang1",
          "wadegiles": "ti⁴ fang¹",
          "bopomofo": "ㄉㄧˋ ㄈㄤ",
          "romatzyh": "dih fang"
        },
        "meanings": [
          "region",
          "regional (away from the central administration)",
          "local"
        ],
        "classifiers": []
      },
      {
        "traditional": "地方",
        "transcriptions": {
          "pinyin": "dì fang",
          "numeric": "di4 fang5",
          "wadegiles": "ti⁴ fang",
          "bopomofo": "ㄉㄧˋ fang",
          "romatzyh": "dih fang"
        },
        "meanings": [
          "area",
          "place",
          "space",
          "room",
          "territory"
        ],
        "classifiers": [
          "处",
          "个",
          "块"
        ]
      }
    ]
  },
  {
    "simplified": "地上",
    "radical": "土",
    "frequency": 2185,
    "pos": [
      "s"
    ],
    "forms": [
      {
        "traditional": "地上",
        "transcriptions": {
          "pinyin": "dì shang",
          "numeric": "di4 shang5",
          "wadegiles": "ti⁴ shang",
          "bopomofo": "ㄉㄧˋ shang",
          "romatzyh": "dih shang"
        },
        "meanings": [
          "on the ground",
          "on the floor"
        ],
        "classifiers": []
      }
    ]
  },
  {
    "simplified": "地图",
    "radical": "土",
    "frequency": 3548,
    "pos": [
      "n"
    ],
    "forms": [
      {
        "traditional": "地圖",
        "transcriptions": {
          "pinyin": "dì tú",
          "numeric": "di4 tu2",
          "wadegiles": "ti⁴ t'u²",
          "bopomofo": "ㄉㄧˋ ㄊㄨˊ",
          "romatzyh": "dih twu"
        },
        "meanings": [
          "map"
        ],
        "classifiers": [
          "张",
          "本"
        ]
      }
    ]
  },
  {
    "simplified": "的",
    "radical": "白",
    "frequency": 1,
    "pos": [
      "u",
      "n"
    ],
    "forms": [
      {
        "traditional": "的",
        "transcriptions": {
          "pinyin": "de",
          "numeric": "de5",
          "wadegiles": "de",
          "bopomofo": "de",
          "romatzyh": "de"
        },
        "meanings": [
          "of; ~'s (possessive particle)",
          "(used after an attribute)",
          "(used to form a nominal expression)",
          "(used at the end of a declarative sentence for emphasis)",
          "also pr. [dì] or [di] in poetry and songs"
        ],
        "classifiers": []
      },
      {
        "traditional": "的",
        "transcriptions": {
          "pinyin": "dī",
          "numeric": "di1",
          "wadegiles": "ti¹",
          "bopomofo": "ㄉㄧ",
          "romatzyh": "di"
        },
        "meanings": [
          "a taxi; a cab (abbr. for 士)"
        ],
        "classifiers": []
      },
      {
        "traditional": "的",
        "transcriptions": {
          "pinyin": "dí",
          "numeric": "di2",
          "wadegiles": "ti²",
          "bopomofo": "ㄉㄧˊ",
          "romatzyh": "dyi"
        },
        "meanings": [
          "really and truly"
        ],
        "classifiers": []
      },
      {
        "traditional": "的",
        "transcriptions": {
          "pinyin": "dì",
          "numeric": "di4",
          "wadegiles": "ti⁴",
          "bopomofo": "ㄉㄧˋ",
          "romatzyh": "dih"
        },
        "meanings": [
          "(bound form) bull's-eye; target"
        ],
        "classifiers": []
      }
    ]
  },
  {
    "simplified": "得到",
    "radical": "彳",
    "frequency": 308,
    "pos": [
      "v"
    ],
    "forms": [
      {
        "traditional": "得到",
        "transcriptions": {
          "pinyin": "dé dào",
          "numeric": "de2 dao4",
          "wadegiles": "te² tao⁴",
          "bopomofo": "ㄉㄜˊ ㄉㄠˋ",
          "romatzyh": "der daw"
        },
        "meanings": [
          "to get",
          "to obtain",
          "to receive"
        ],
        "classifiers": []
      }
    ]
  },
  {
    "simplified": "等",
    "radical": "⺮",
    "frequency": 83,
    "pos": [
      "v",
      "u"
    ],
    "forms": [
      {
        "traditional": "等",
        "transcriptions": {
          "pinyin": "děng",
          "numeric": "deng3",
          "wadegiles": "teng³",
          "bopomofo": "ㄉㄥˇ",
          "romatzyh": "deeng"
        },
        "meanings": [
          "class",
          "rank",
          "grade",
          "equal to",
          "same as",
          "to wait for",
          "to await",
          "et cetera",
          "and so on",
          "et al. (and other authors)",
          "after",
          "as soon as",
          "once"
        ],
        "classifiers": []
      }
    ]
  },
  {
    "simplified": "弟",
    "radical": "弓",
    "frequency": 6568,
    "pos": [
      "n"
    ],
    "forms": [
      {
        "traditional": "弟",
        "transcriptions": {
          "pinyin": "dì",
          "numeric": "di4",
          "wadegiles": "ti⁴",
          "bopomofo": "ㄉㄧˋ",
          "romatzyh": "dih"
        },
        "meanings": [
          "younger brother",
          "junior male",
          "I (modest word in letter)"
        ],
        "classifiers": []
      },
      {
        "traditional": "弟",
        "transcriptions": {
          "pinyin": "tì",
          "numeric": "ti4",
          "wadegiles": "t'i⁴",
          "bopomofo": "ㄊㄧˋ",
          "romatzyh": "tih"
        },
        "meanings": [
          "variant of 悌"
        ],
        "classifiers": []
      }
    ]
  },
  {
    "simplified": "弟弟",
    "radical": "弓",
    "frequency": 2424,
    "pos": [
      "n"
    ],
    "forms": [
      {
        "traditional": "弟弟",
        "transcriptions": {
          "pinyin": "dì di",
          "numeric": "di4 di5",
          "wadegiles": "ti⁴ di",
          "bopomofo": "ㄉㄧˋ di",
          "romatzyh": "dih di"
        },
        "meanings": [
          "younger brother"
        ],
        "classifiers": [
          "个",
          "位"
        ]
      }
    ]
  }
]